mimic_da/__init__.py
mimic_da/miMic_test.py
mimic_da/tax_tree_create.py
mimic_da-1.0.1.dist-info/LICENSE.txt
mimic_da-1.0.1.dist-info/WHEEL
mimic_da-1.0.1.dist-info/METADATA
mimic_da-1.0.1.dist-info/RECORD
