Metadata-Version: 2.1
Name: mimic-da
Version: 1.0.1
Summary: 
Keywords: Diffrential analysis,cladogram,Mann-Whitney,microbiome
Author-email: "Oshrit Shtossel, Shani Finkelstein" <oshritvig@gmail.com>
Requires-Python: >=3.8
Classifier: License :: OSI Approved :: GNU Lesser General Public License v3 or later (LGPLv3+)
Classifier: Programming Language :: Python
Classifier: Programming Language :: Python :: 3
Requires-Dist: samba-metric>=0.0.13
Requires-Dist: MIPMLP>=1.2.17
Requires-Dist: pyqt5==5.15.10
Requires-Dist: ete3==3.1.3
Requires-Dist: statsmodels>=0.14.0
